midipacks/__init__.py
midipacks/pack.py
midipacks-0.0.1.dist-info/DESCRIPTION.rst
midipacks-0.0.1.dist-info/METADATA
midipacks-0.0.1.dist-info/RECORD
midipacks-0.0.1.dist-info/WHEEL
midipacks-0.0.1.dist-info/metadata.json
midipacks-0.0.1.dist-info/top_level.txt
