Metadata-Version: 2.0
Name: midipacks
Version: 0.0.1
Summary: Packets over MIDI
Home-page: https://github.com/prashnts/midipacks
Author: Prashant Sinha
Author-email: prashant@noop.pw
License: MIT
Download-URL: https://github.com/prashnts/midipacks/tarball/0.0.1
Platform: UNKNOWN
Classifier: Development Status :: 3 - Alpha
Classifier: Intended Audience :: Developers
Classifier: License :: OSI Approved :: MIT License
Classifier: Programming Language :: Python
Classifier: Programming Language :: Python :: 2
Classifier: Programming Language :: Python :: 2.7
Classifier: Programming Language :: Python :: 3
Classifier: Programming Language :: Python :: 3.3
Classifier: Programming Language :: Python :: 3.4
Classifier: Topic :: Software Development :: Libraries :: Python Modules
Requires-Dist: mido
Requires-Dist: python-rtmidi
